{"cover":false,"categories":{"Candies - Sweets":{"name":"Candies - Sweets","cover":{"name":"Candies - Sweets","category":"Candies - Sweets","image":"Candies - Sweets.jpg","audio":"Candies - Sweets.mp3"},"cards":[{"name":"Bubble gum","category":"Candies - Sweets","image":"bubble gum.jpg","audio":"bubble gum.mp3"},{"name":"Candy cane","category":"Candies - Sweets","image":"candy cane.jpg","audio":"candy cane.mp3"},{"name":"Candy corn","category":"Candies - Sweets","image":"candy corn.jpg","audio":"candy corn.mp3"},{"name":"Chewing gum","category":"Candies - Sweets","image":"chewing gum.jpg","audio":"chewing gum.mp3"},{"name":"Chocolate bar","category":"Candies - Sweets","image":"chocolate bar.jpg","audio":"chocolate bar.mp3"},{"name":"Chocolate drops","category":"Candies - Sweets","image":"chocolate drops.jpg","audio":"chocolate drops.mp3"},{"name":"Chocolate truffles","category":"Candies - Sweets","image":"chocolate truffles.jpg","audio":"chocolate truffles.mp3"},{"name":"Cookies","category":"Candies - Sweets","image":"cookies.jpg","audio":"cookies.mp3"},{"name":"Cotton candy","category":"Candies - Sweets","image":"cotton candy.jpg","audio":"cotton candy.mp3"},{"name":"Cream puff","category":"Candies - Sweets","image":"cream puff.jpg","audio":"cream puff.mp3"},{"name":"Cupcake","category":"Candies - Sweets","image":"cupcake.jpg","audio":"cupcake.mp3"},{"name":"Doughnuts (donuts)","category":"Candies - Sweets","image":"doughnuts (donuts).jpg","audio":"doughnuts (donuts).mp3"},{"name":"Filled biscuits","category":"Candies - Sweets","image":"filled biscuits.jpg","audio":"filled biscuits.mp3"},{"name":"Gumdrops","category":"Candies - Sweets","image":"gumdrops.jpg","audio":"gumdrops.mp3"},{"name":"Gummy bears","category":"Candies - Sweets","image":"gummy bears.jpg","audio":"gummy bears.mp3"},{"name":"Hard candies","category":"Candies - Sweets","image":"hard candies.jpg","audio":"hard candies.mp3"},{"name":"Ice cream","category":"Candies - Sweets","image":"ice cream.jpg","audio":"ice cream.mp3"},{"name":"Jelly beans","category":"Candies - Sweets","image":"jelly beans.jpg","audio":"jelly beans.mp3"},{"name":"M&ms","category":"Candies - Sweets","image":"m&ms.jpg","audio":false},{"name":"Marshmallow","category":"Candies - Sweets","image":"marshmallow.jpg","audio":"marshmallow.mp3"},{"name":"Peanut brittle","category":"Candies - Sweets","image":"peanut brittle.jpg","audio":"peanut brittle.mp3"},{"name":"Popsicle","category":"Candies - Sweets","image":"popsicle.jpg","audio":"popsicle.mp3"},{"name":"Sugar cookies","category":"Candies - Sweets","image":"sugar cookies.jpg","audio":"sugar cookies.mp3"},{"name":"Wafer","category":"Candies - Sweets","image":"wafer.jpg","audio":"wafer.mp3"}]},"City Places - City Spots":{"name":"City Places - City Spots","cover":{"name":"City Places - City Spots","category":"City Places - City Spots","image":"City Places - City Spots.jpg","audio":"City Places - City Spots.mp3"},"cards":[{"name":"Airport","category":"City Places - City Spots","image":"airport.jpg","audio":"airport.mp3"},{"name":"Bakery","category":"City Places - City Spots","image":"bakery.jpg","audio":"bakery.mp3"},{"name":"Bank","category":"City Places - City Spots","image":"bank.jpg","audio":"bank.mp3"},{"name":"Beauty salon","category":"City Places - City Spots","image":"beauty salon.jpg","audio":"beauty salon.mp3"},{"name":"Bookstore","category":"City Places - City Spots","image":"bookstore.jpg","audio":"bookstore.mp3"},{"name":"Bus station","category":"City Places - City Spots","image":"bus station.jpg","audio":"bus station.mp3"},{"name":"Bus stop","category":"City Places - City Spots","image":"bus stop.jpg","audio":"bus stop.mp3"},{"name":"Butchery","category":"City Places - City Spots","image":"butchery.jpg","audio":"butchery.mp3"},{"name":"Cemetery","category":"City Places - City Spots","image":"cemetery.jpg","audio":"cemetery.mp3"},{"name":"Church","category":"City Places - City Spots","image":"church.jpg","audio":"church.mp3"},{"name":"City hall","category":"City Places - City Spots","image":"city hall.jpg","audio":"city hall.mp3"},{"name":"Clothes shop (store)","category":"City Places - City Spots","image":"clothes shop (store).jpg","audio":"clothes shop (store).mp3"},{"name":"College (graduation gown)","category":"City Places - City Spots","image":"college (graduation gown).jpg","audio":"college (graduation gown).mp3"},{"name":"Day care","category":"City Places - City Spots","image":"day care.jpg","audio":"day care.mp3"},{"name":"Dentist office","category":"City Places - City Spots","image":"dentist office.jpg","audio":"dentist office.mp3"},{"name":"English school","category":"City Places - City Spots","image":"english school.jpg","audio":"english school.mp3"},{"name":"Factory","category":"City Places - City Spots","image":"factory.jpg","audio":"factory.mp3"},{"name":"Fast food","category":"City Places - City Spots","image":"fast food.jpg","audio":"fast food.mp3"},{"name":"Fire station","category":"City Places - City Spots","image":"fire station.jpg","audio":"fire station.mp3"},{"name":"Flower shop","category":"City Places - City Spots","image":"flower shop.jpg","audio":"flower shop.mp3"},{"name":"Gas station","category":"City Places - City Spots","image":"gas station.jpg","audio":"gas station.mp3"},{"name":"Grocery store","category":"City Places - City Spots","image":"grocery store.jpg","audio":"grocery store.mp3"},{"name":"Gym","category":"City Places - City Spots","image":"gym.jpg","audio":"gym.mp3"},{"name":"Hospital","category":"City Places - City Spots","image":"hospital.jpg","audio":"hospital.mp3"},{"name":"Hotel","category":"City Places - City Spots","image":"hotel.jpg","audio":"hotel.mp3"},{"name":"Library","category":"City Places - City Spots","image":"library.jpg","audio":"library.mp3"},{"name":"Museum","category":"City Places - City Spots","image":"museum.jpg","audio":"museum.mp3"},{"name":"Newsstand","category":"City Places - City Spots","image":"newsstand.jpg","audio":"newsstand.mp3"},{"name":"Park","category":"City Places - City Spots","image":"park.jpg","audio":"park.mp3"},{"name":"Parking lot","category":"City Places - City Spots","image":"parking lot.jpg","audio":"parking lot.mp3"},{"name":"Pet shop","category":"City Places - City Spots","image":"pet shop.jpg","audio":"pet shop.mp3"},{"name":"Pharmacy","category":"City Places - City Spots","image":"pharmacy.jpg","audio":"pharmacy.mp3"},{"name":"Playground","category":"City Places - City Spots","image":"playground.jpg","audio":"playground.mp3"},{"name":"Police station","category":"City Places - City Spots","image":"police station.jpg","audio":"police station.mp3"},{"name":"Post office","category":"City Places - City Spots","image":"post office.jpg","audio":"post office.mp3"},{"name":"Restaurant","category":"City Places - City Spots","image":"restaurant.jpg","audio":"restaurant.mp3"},{"name":"Shoe shop (store)","category":"City Places - City Spots","image":"shoe shop (store).jpg","audio":"shoe shop (store).mp3"},{"name":"Square (public square)","category":"City Places - City Spots","image":"square (public square).jpg","audio":"square (public square).mp3"},{"name":"Stadium","category":"City Places - City Spots","image":"stadium.jpg","audio":"stadium.mp3"},{"name":"Subway","category":"City Places - City Spots","image":"subway.jpg","audio":"subway.mp3"},{"name":"Supermarket","category":"City Places - City Spots","image":"supermarket.jpg","audio":"supermarket.mp3"},{"name":"Theater","category":"City Places - City Spots","image":"theater.jpg","audio":"theater.mp3"},{"name":"Train station","category":"City Places - City Spots","image":"train station.jpg","audio":"train station.mp3"},{"name":"Zoo","category":"City Places - City Spots","image":"zoo.jpg","audio":"zoo.mp3"}]},"Clothes - Clothing":{"name":"Clothes - Clothing","cover":{"name":"Clothes - Clothing","category":"Clothes - Clothing","image":"Clothes - Clothing.jpg","audio":"Clothes - Clothing.mp3"},"cards":[{"name":"Bathing suit","category":"Clothes - Clothing","image":"bathing suit.jpg","audio":"bathing suit.mp3"},{"name":"Bikini","category":"Clothes - Clothing","image":"bikini.jpg","audio":"bikini.mp3"},{"name":"Blouse","category":"Clothes - Clothing","image":"blouse.jpg","audio":"blouse.mp3"},{"name":"Coat","category":"Clothes - Clothing","image":"coat.jpg","audio":"coat.mp3"},{"name":"Dress","category":"Clothes - Clothing","image":"dress.jpg","audio":"dress.mp3"},{"name":"Flip flops","category":"Clothes - Clothing","image":"flip flops.jpg","audio":"flip flops.mp3"},{"name":"Gloves","category":"Clothes - Clothing","image":"gloves.jpg","audio":"gloves.mp3"},{"name":"Gown","category":"Clothes - Clothing","image":"gown.jpg","audio":"gown.mp3"},{"name":"Handbag","category":"Clothes - Clothing","image":"handbag.jpg","audio":"handbag.mp3"},{"name":"Hat","category":"Clothes - Clothing","image":"hat.jpg","audio":"hat.mp3"},{"name":"Hoodie jacket","category":"Clothes - Clothing","image":"hoodie jacket.jpg","audio":"hoodie jacket.mp3"},{"name":"Jacket","category":"Clothes - Clothing","image":"jacket.jpg","audio":"jacket.mp3"},{"name":"Jeans","category":"Clothes - Clothing","image":"jeans.jpg","audio":"jeans.mp3"},{"name":"Long-sleeve shirt","category":"Clothes - Clothing","image":"long-sleeve shirt.jpg","audio":"long-sleeve shirt.mp3"},{"name":"Office Suit","category":"Clothes - Clothing","image":"Office Suit.jpg","audio":"Office Suit.mp3"},{"name":"Pajamas","category":"Clothes - Clothing","image":"pajamas.jpg","audio":"pajamas.mp3"},{"name":"Pants","category":"Clothes - Clothing","image":"pants.jpg","audio":"pants.mp3"},{"name":"Shirt","category":"Clothes - Clothing","image":"shirt.jpg","audio":"shirt.mp3"},{"name":"Shoes","category":"Clothes - Clothing","image":"shoes.jpg","audio":"shoes.mp3"},{"name":"Shorts","category":"Clothes - Clothing","image":"shorts.jpg","audio":"shorts.mp3"},{"name":"Skirt","category":"Clothes - Clothing","image":"skirt.jpg","audio":"skirt.mp3"},{"name":"Socks","category":"Clothes - Clothing","image":"socks.jpg","audio":"socks.mp3"},{"name":"Suit jacket","category":"Clothes - Clothing","image":"suit jacket.jpg","audio":"suit jacket.mp3"},{"name":"Suit","category":"Clothes - Clothing","image":"suit.jpg","audio":"suit.mp3"},{"name":"Sweat shirt","category":"Clothes - Clothing","image":"sweat shirt.jpg","audio":"sweat shirt.mp3"},{"name":"Sweater","category":"Clothes - Clothing","image":"sweater.jpg","audio":"sweater.mp3"},{"name":"T-shirt","category":"Clothes - Clothing","image":"T-shirt.jpg","audio":"T-shirt.mp3"},{"name":"Tank top","category":"Clothes - Clothing","image":"tank top.jpg","audio":"tank top.mp3"},{"name":"Tie","category":"Clothes - Clothing","image":"tie.jpg","audio":"tie.mp3"},{"name":"Underpants","category":"Clothes - Clothing","image":"underpants.jpg","audio":"underpants.mp3"}]},"Farm Animals":{"name":"Farm Animals","cover":{"name":"Farm Animals","category":"Farm Animals","image":"Farm Animals.jpg","audio":"Farm Animals.mp3"},"cards":[{"name":"Baby Cow","category":"Farm Animals","image":"Baby Cow.jpg","audio":"Baby Cow.mp3"},{"name":"Bull","category":"Farm Animals","image":"Bull.jpg","audio":"Bull.mp3"},{"name":"Bunny","category":"Farm Animals","image":"Bunny.jpg","audio":"Bunny.mp3"},{"name":"Cat","category":"Farm Animals","image":"cat.jpg","audio":"cat.mp3"},{"name":"Chicken","category":"Farm Animals","image":"chicken.jpg","audio":"chicken.mp3"},{"name":"Chicks","category":"Farm Animals","image":"chicks.jpg","audio":"chicks.mp3"},{"name":"Cow","category":"Farm Animals","image":"cow.jpg","audio":"cow.mp3"},{"name":"Dog","category":"Farm Animals","image":"dog.jpg","audio":"dog.mp3"},{"name":"Duck","category":"Farm Animals","image":"duck.jpg","audio":"duck.mp3"},{"name":"Ducklings","category":"Farm Animals","image":"ducklings.jpg","audio":"ducklings.mp3"},{"name":"Goat","category":"Farm Animals","image":"goat.jpg","audio":"goat.mp3"},{"name":"Golden fish","category":"Farm Animals","image":"golden fish.jpg","audio":"golden fish.mp3"},{"name":"Goose","category":"Farm Animals","image":"goose.jpg","audio":"goose.mp3"},{"name":"Guinea fowl","category":"Farm Animals","image":"guinea fowl.jpg","audio":"guinea fowl.mp3"},{"name":"Guinea pig","category":"Farm Animals","image":"guinea pig.jpg","audio":"guinea pig.mp3"},{"name":"Hen & chicks","category":"Farm Animals","image":"hen & chicks.jpg","audio":"hen & chicks.mp3"},{"name":"Horse","category":"Farm Animals","image":"horse.jpg","audio":"horse.mp3"},{"name":"Kitten","category":"Farm Animals","image":"kitten.jpg","audio":"kitten.mp3"},{"name":"Lamb","category":"Farm Animals","image":"lamb.jpg","audio":"lamb.mp3"},{"name":"Pig","category":"Farm Animals","image":"pig.jpg","audio":"pig.mp3"},{"name":"Piglet","category":"Farm Animals","image":"piglet.jpg","audio":"piglet.mp3"},{"name":"Pony","category":"Farm Animals","image":"pony.jpg","audio":"pony.mp3"},{"name":"Puppy","category":"Farm Animals","image":"puppy.jpg","audio":"puppy.mp3"},{"name":"Rabbit","category":"Farm Animals","image":"rabbit.jpg","audio":"rabbit.mp3"},{"name":"Rooster","category":"Farm Animals","image":"rooster.jpg","audio":"rooster.mp3"},{"name":"Sheep","category":"Farm Animals","image":"sheep.jpg","audio":"sheep.mp3"},{"name":"Turkey","category":"Farm Animals","image":"turkey.jpg","audio":"turkey.mp3"}]},"Food and Drink":{"name":"Food and Drink","cover":{"name":"Food and Drink","category":"Food and Drink","image":"Food and Drink.jpg","audio":"Food and Drink.mp3"},"cards":[{"name":"Barbecue","category":"Food and Drink","image":"barbecue.jpg","audio":"barbecue.mp3"},{"name":"Beef","category":"Food and Drink","image":"beef.jpg","audio":"beef.mp3"},{"name":"Beer","category":"Food and Drink","image":"beer.jpg","audio":"beer.mp3"},{"name":"Boiled egg","category":"Food and Drink","image":"boiled egg.jpg","audio":"boiled egg.mp3"},{"name":"Bread rolls","category":"Food and Drink","image":"bread rolls.jpg","audio":"bread rolls.mp3"},{"name":"Bread","category":"Food and Drink","image":"bread.jpg","audio":"bread.mp3"},{"name":"Butter","category":"Food and Drink","image":"butter.jpg","audio":"butter.mp3"},{"name":"Cake","category":"Food and Drink","image":"cake.jpg","audio":"cake.mp3"},{"name":"Cheese","category":"Food and Drink","image":"cheese.jpg","audio":"cheese.mp3"},{"name":"Chicken","category":"Food and Drink","image":"chicken.jpg","audio":"chicken.mp3"},{"name":"Coffee","category":"Food and Drink","image":"coffee.jpg","audio":"coffee.mp3"},{"name":"Corn flour","category":"Food and Drink","image":"corn flour.jpg","audio":"corn flour.mp3"},{"name":"Fish","category":"Food and Drink","image":"fish.jpg","audio":"fish.mp3"},{"name":"Flour","category":"Food and Drink","image":"flour.jpg","audio":"flour.mp3"},{"name":"Fried egg","category":"Food and Drink","image":"fried egg.jpg","audio":"fried egg.mp3"},{"name":"Fries","category":"Food and Drink","image":"fries.jpg","audio":"fries.mp3"},{"name":"Fruit juice","category":"Food and Drink","image":"fruit juice.jpg","audio":"fruit juice.mp3"},{"name":"Ham","category":"Food and Drink","image":"ham.jpg","audio":"ham.mp3"},{"name":"Hamburger","category":"Food and Drink","image":"hamburger.jpg","audio":"hamburger.mp3"},{"name":"Honey","category":"Food and Drink","image":"honey.jpg","audio":"honey.mp3"},{"name":"Ketchup","category":"Food and Drink","image":"ketchup.jpg","audio":"ketchup.mp3"},{"name":"Lasanga","category":"Food and Drink","image":"lasanga.jpg","audio":"lasanga.mp3"},{"name":"Lemonade","category":"Food and Drink","image":"lemonade.jpg","audio":"lemonade.mp3"},{"name":"Margarine","category":"Food and Drink","image":"margarine.jpg","audio":"margarine.mp3"},{"name":"Mashed potatoes","category":"Food and Drink","image":"mashed potatoes.jpg","audio":"mashed potatoes.mp3"},{"name":"Mayonnaise","category":"Food and Drink","image":"mayonnaise.jpg","audio":"mayonnaise.mp3"},{"name":"Meat ball","category":"Food and Drink","image":"meat ball.jpg","audio":"meat ball.mp3"},{"name":"Meat","category":"Food and Drink","image":"meat.jpg","audio":"meat.mp3"},{"name":"Milk","category":"Food and Drink","image":"milk.jpg","audio":"milk.mp3"},{"name":"Pancake","category":"Food and Drink","image":"pancake.jpg","audio":"pancake.mp3"},{"name":"Pasta","category":"Food and Drink","image":"pasta.jpg","audio":"pasta.mp3"},{"name":"Pie","category":"Food and Drink","image":"pie.jpg","audio":"pie.mp3"},{"name":"Pizza","category":"Food and Drink","image":"pizza.jpg","audio":"pizza.mp3"},{"name":"Potato","category":"Food and Drink","image":"potato.jpg","audio":"potato.mp3"},{"name":"Pudding","category":"Food and Drink","image":"pudding.jpg","audio":"pudding.mp3"},{"name":"Rice & beans","category":"Food and Drink","image":"rice & beans.jpg","audio":"rice & beans.mp3"},{"name":"Salad","category":"Food and Drink","image":"salad.jpg","audio":"salad.mp3"},{"name":"Sandwich","category":"Food and Drink","image":"sandwich.jpg","audio":"sandwich.mp3"},{"name":"Sausage","category":"Food and Drink","image":"sausage.jpg","audio":"sausage.mp3"},{"name":"Seafood","category":"Food and Drink","image":"seafood.jpg","audio":"seafood.mp3"},{"name":"Soda","category":"Food and Drink","image":"soda.jpg","audio":"soda.mp3"},{"name":"Soft drink","category":"Food and Drink","image":"soft drink.jpg","audio":"soft drink.mp3"},{"name":"Soup","category":"Food and Drink","image":"soup.jpg","audio":"soup.mp3"},{"name":"Spaghetti","category":"Food and Drink","image":"spaghetti.jpg","audio":"spaghetti.mp3"},{"name":"Spice","category":"Food and Drink","image":"spice.jpg","audio":"spice.mp3"},{"name":"Steak","category":"Food and Drink","image":"steak.jpg","audio":"steak.mp3"},{"name":"Stroganoff","category":"Food and Drink","image":"stroganoff.jpg","audio":"stroganoff.mp3"},{"name":"Sugar","category":"Food and Drink","image":"sugar.jpg","audio":"sugar.mp3"},{"name":"Tea","category":"Food and Drink","image":"tea.jpg","audio":"tea.mp3"},{"name":"Toast","category":"Food and Drink","image":"toast.jpg","audio":"toast.mp3"},{"name":"Tooth pick","category":"Food and Drink","image":"tooth pick.jpg","audio":"tooth pick.mp3"},{"name":"Vegetables","category":"Food and Drink","image":"vegetables.jpg","audio":"vegetables.mp3"},{"name":"Water","category":"Food and Drink","image":"water.jpg","audio":"water.mp3"},{"name":"Wine","category":"Food and Drink","image":"wine.jpg","audio":"wine.mp3"}]},"Fruit":{"name":"Fruit","cover":{"name":"Fruit","category":"Fruit","image":"Fruit.jpg","audio":"Fruit.mp3"},"cards":[{"name":"Apple","category":"Fruit","image":"apple.jpg","audio":"apple.mp3"},{"name":"Avocado","category":"Fruit","image":"avocado.jpg","audio":"avocado.mp3"},{"name":"Banana","category":"Fruit","image":"banana.jpg","audio":"banana.mp3"},{"name":"Cherry","category":"Fruit","image":"cherry.jpg","audio":"cherry.mp3"},{"name":"Coconut","category":"Fruit","image":"coconut.jpg","audio":"coconut.mp3"},{"name":"Dates","category":"Fruit","image":"dates.jpg","audio":"dates.mp3"},{"name":"Dragon fruit","category":"Fruit","image":"dragon fruit.jpg","audio":"dragon fruit.mp3"},{"name":"Fig","category":"Fruit","image":"fig.jpg","audio":"fig.mp3"},{"name":"Grapes","category":"Fruit","image":"grapes.jpg","audio":"grapes.mp3"},{"name":"Jackfruit","category":"Fruit","image":"jackfruit.jpg","audio":"jackfruit.mp3"},{"name":"Kiwi","category":"Fruit","image":"kiwi.jpg","audio":"kiwi.mp3"},{"name":"Lemon","category":"Fruit","image":"lemon.jpg","audio":"lemon.mp3"},{"name":"Mango","category":"Fruit","image":"mango.jpg","audio":"mango.mp3"},{"name":"Melon","category":"Fruit","image":"melon.jpg","audio":"melon.mp3"},{"name":"Olive","category":"Fruit","image":"olive.jpg","audio":"olive.mp3"},{"name":"Orange","category":"Fruit","image":"orange.jpg","audio":"orange.mp3"},{"name":"Papaya","category":"Fruit","image":"papaya.jpg","audio":"papaya.mp3"},{"name":"Parsimon","category":"Fruit","image":"parsimon.jpg","audio":"parsimon.mp3"},{"name":"Passion fruit","category":"Fruit","image":"passion fruit.jpg","audio":"passion fruit.mp3"},{"name":"Peach","category":"Fruit","image":"peach.jpg","audio":"peach.mp3"},{"name":"Pear","category":"Fruit","image":"pear.jpg","audio":"pear.mp3"},{"name":"Pineapple","category":"Fruit","image":"pineapple.jpg","audio":"pineapple.mp3"},{"name":"Plum","category":"Fruit","image":"plum.jpg","audio":"plum.mp3"},{"name":"Pomegranate","category":"Fruit","image":"pomegranate.jpg","audio":"pomegranate.mp3"},{"name":"Pumpkin","category":"Fruit","image":"pumpkin.jpg","audio":"pumpkin.mp3"},{"name":"Raspberry","category":"Fruit","image":"raspberry.jpg","audio":"raspberry.mp3"},{"name":"Strawberry","category":"Fruit","image":"strawberry.jpg","audio":"strawberry.mp3"},{"name":"Tangerine","category":"Fruit","image":"tangerine.jpg","audio":"tangerine.mp3"},{"name":"Watermelon","category":"Fruit","image":"watermelon.jpg","audio":"watermelon.mp3"}]},"Furniture":{"name":"Furniture","cover":{"name":"Furniture","category":"Furniture","image":"Furniture.jpg","audio":"Furniture.mp3"},"cards":[{"name":"Armchair","category":"Furniture","image":"armchair.jpg","audio":false},{"name":"Bed","category":"Furniture","image":"bed.jpg","audio":false},{"name":"Bench","category":"Furniture","image":"bench.jpg","audio":false},{"name":"Bookshelf","category":"Furniture","image":"bookshelf.jpg","audio":false},{"name":"Bunk bed","category":"Furniture","image":"bunk bed.jpg","audio":false},{"name":"Cabinets","category":"Furniture","image":"cabinets.jpg","audio":false},{"name":"Chair","category":"Furniture","image":"chair.jpg","audio":false},{"name":"Closet","category":"Furniture","image":"closet.jpg","audio":false},{"name":"Coat rack","category":"Furniture","image":"coat rack.jpg","audio":false},{"name":"Coffee table","category":"Furniture","image":"coffee table.jpg","audio":false},{"name":"Couch","category":"Furniture","image":"couch.jpg","audio":false},{"name":"Cradle","category":"Furniture","image":"cradle.jpg","audio":false},{"name":"Crib","category":"Furniture","image":"crib.jpg","audio":false},{"name":"Drawer","category":"Furniture","image":"drawer.jpg","audio":false},{"name":"Dresser","category":"Furniture","image":"dresser.jpg","audio":false},{"name":"Hammock","category":"Furniture","image":"hammock.jpg","audio":false},{"name":"Ironing board","category":"Furniture","image":"ironing board.jpg","audio":false},{"name":"Nightstand","category":"Furniture","image":"nightstand.jpg","audio":false},{"name":"Rocking chair","category":"Furniture","image":"rocking chair.jpg","audio":false},{"name":"Shelf","category":"Furniture","image":"shelf.jpg","audio":false},{"name":"Sofa bed","category":"Furniture","image":"sofa bed.jpg","audio":false},{"name":"Sofa","category":"Furniture","image":"sofa.jpg","audio":false},{"name":"Stools","category":"Furniture","image":"stools.jpg","audio":false},{"name":"Swivel chair","category":"Furniture","image":"swivel chair.jpg","audio":false},{"name":"Table","category":"Furniture","image":"table.jpg","audio":false},{"name":"TV Rack","category":"Furniture","image":"TV Rack.jpg","audio":false}]},"House":{"name":"House","cover":false,"cards":[{"name":"Attic","category":"House","image":"attic.jpg","audio":false},{"name":"Balcony","category":"House","image":"balcony.jpg","audio":false},{"name":"Basement","category":"House","image":"basement.jpg","audio":false},{"name":"Bathroom","category":"House","image":"bathroom.jpg","audio":false},{"name":"Bedroom","category":"House","image":"bedroom.jpg","audio":false},{"name":"Ceiling","category":"House","image":"ceiling.jpg","audio":false},{"name":"Chimney","category":"House","image":"chimney.jpg","audio":false},{"name":"Dining room","category":"House","image":"dining room.jpg","audio":false},{"name":"Door","category":"House","image":"door.jpg","audio":false},{"name":"Downstairs","category":"House","image":"downstairs.jpg","audio":false},{"name":"Driveway","category":"House","image":"driveway.jpg","audio":false},{"name":"Fireplace","category":"House","image":"fireplace.jpg","audio":false},{"name":"Front porch","category":"House","image":"front porch.jpg","audio":false},{"name":"Garage","category":"House","image":"garage.jpg","audio":false},{"name":"Garden wall","category":"House","image":"garden wall.jpg","audio":false},{"name":"Garden","category":"House","image":"garden.jpg","audio":false},{"name":"Gate","category":"House","image":"gate.jpg","audio":false},{"name":"Kitchen","category":"House","image":"kitchen.jpg","audio":false},{"name":"Laundry room","category":"House","image":"laundry room.jpg","audio":false},{"name":"Living room","category":"House","image":"living room.jpg","audio":false},{"name":"Mailbox","category":"House","image":"mailbox.jpg","audio":false},{"name":"Messi room","category":"House","image":"messi room.jpg","audio":false},{"name":"Roof","category":"House","image":"roof.jpg","audio":false},{"name":"Steps","category":"House","image":"steps.jpg","audio":false},{"name":"Study","category":"House","image":"study.jpg","audio":false},{"name":"Swimming pool","category":"House","image":"swimming pool.jpg","audio":false},{"name":"Upstairs","category":"House","image":"upstairs.jpg","audio":false},{"name":"Walkway","category":"House","image":"walkway.jpg","audio":false},{"name":"Window","category":"House","image":"window.jpg","audio":false}]},"In the Bathroom":{"name":"In the Bathroom","cover":{"name":"In the Bathroom","category":"In the Bathroom","image":"In the Bathroom.jpg","audio":"In the Bathroom.mp3"},"cards":[{"name":"Bathrobe","category":"In the Bathroom","image":"bathrobe.jpg","audio":"bathrobe.mp3"},{"name":"Bathroom box","category":"In the Bathroom","image":"bathroom box.jpg","audio":"bathroom box.mp3"},{"name":"Bathtub","category":"In the Bathroom","image":"bathtub.jpg","audio":"bathtub.mp3"},{"name":"Cabinet","category":"In the Bathroom","image":"cabinet.jpg","audio":"cabinet.mp3"},{"name":"Comb","category":"In the Bathroom","image":"comb.jpg","audio":"comb.mp3"},{"name":"Drain","category":"In the Bathroom","image":"drain.jpg","audio":"drain.mp3"},{"name":"Electric razor","category":"In the Bathroom","image":"electric razor.jpg","audio":"electric razor.mp3"},{"name":"Hair brush","category":"In the Bathroom","image":"hair brush.jpg","audio":"hair brush.mp3"},{"name":"Hair dryer","category":"In the Bathroom","image":"hair dryer.jpg","audio":"hair dryer.mp3"},{"name":"Liquid soap","category":"In the Bathroom","image":"liquid soap.jpg","audio":"liquid soap.mp3"},{"name":"Makeup kit","category":"In the Bathroom","image":"makeup kit.jpg","audio":"makeup kit.mp3"},{"name":"Mirror","category":"In the Bathroom","image":"mirror.jpg","audio":"mirror.mp3"},{"name":"Plunger","category":"In the Bathroom","image":"plunger.jpg","audio":"plunger.mp3"},{"name":"Razor","category":"In the Bathroom","image":"razor.jpg","audio":"razor.mp3"},{"name":"Scale","category":"In the Bathroom","image":"scale.jpg","audio":"scale.mp3"},{"name":"Shampoo & conditioner","category":"In the Bathroom","image":"shampoo & conditioner.jpg","audio":"shampoo & conditioner.mp3"},{"name":"Shower","category":"In the Bathroom","image":"shower.jpg","audio":"shower.mp3"},{"name":"Soap dispenser (conteiner)","category":"In the Bathroom","image":"soap dispenser (conteiner).jpg","audio":"soap dispenser (conteiner).mp3"},{"name":"Toilet paper holder","category":"In the Bathroom","image":"toilet paper holder.jpg","audio":"toilet paper holder.mp3"},{"name":"Toilet paper","category":"In the Bathroom","image":"toilet paper.jpg","audio":"toilet paper.mp3"},{"name":"Toilet seat (cover - lid)","category":"In the Bathroom","image":"toilet seat (cover - lid).jpg","audio":"toilet seat (cover - lid).mp3"},{"name":"Toilet soap","category":"In the Bathroom","image":"toilet soap.jpg","audio":"toilet soap.mp3"},{"name":"Toilet","category":"In the Bathroom","image":"toilet.jpg","audio":"toilet.mp3"},{"name":"Toothbrush","category":"In the Bathroom","image":"toothbrush.jpg","audio":"toothbrush.mp3"},{"name":"Toothpaste","category":"In the Bathroom","image":"toothpaste.jpg","audio":"toothpaste.mp3"},{"name":"Towel rack","category":"In the Bathroom","image":"towel rack.jpg","audio":"towel rack.mp3"},{"name":"Wash basin","category":"In the Bathroom","image":"wash basin.jpg","audio":"wash basin.mp3"}]},"In the Kitchen":{"name":"In the Kitchen","cover":{"name":"In the Kitchen","category":"In the Kitchen","image":"In the Kitchen.jpg","audio":"In the Kitchen.mp3"},"cards":[{"name":"Apron","category":"In the Kitchen","image":"apron.jpg","audio":"apron.mp3"},{"name":"Baking sheet (baking dish)","category":"In the Kitchen","image":"baking sheet (baking dish).jpg","audio":"baking sheet (baking dish).mp3"},{"name":"Blender","category":"In the Kitchen","image":"blender.jpg","audio":"blender.mp3"},{"name":"Bowl","category":"In the Kitchen","image":"bowl.jpg","audio":"bowl.mp3"},{"name":"Burner","category":"In the Kitchen","image":"burner.jpg","audio":"burner.mp3"},{"name":"Chopper","category":"In the Kitchen","image":"chopper.jpg","audio":"chopper.mp3"},{"name":"Colander","category":"In the Kitchen","image":"colander.jpg","audio":"colander.mp3"},{"name":"Cup and saucer","category":"In the Kitchen","image":"cup and saucer.jpg","audio":"cup and saucer.mp3"},{"name":"Cupboard","category":"In the Kitchen","image":"cupboard.jpg","audio":"cupboard.mp3"},{"name":"Cutting board","category":"In the Kitchen","image":"cutting board.jpg","audio":"cutting board.mp3"},{"name":"Detergent","category":"In the Kitchen","image":"detergent.jpg","audio":"detergent.mp3"},{"name":"Dish dryer","category":"In the Kitchen","image":"dish dryer.jpg","audio":"dish dryer.mp3"},{"name":"Dish soap","category":"In the Kitchen","image":"dish soap.jpg","audio":"dish soap.mp3"},{"name":"Dish towel","category":"In the Kitchen","image":"dish towel.jpg","audio":"dish towel.mp3"},{"name":"Dishcloth","category":"In the Kitchen","image":"dishcloth.jpg","audio":"dishcloth.mp3"},{"name":"Dishes","category":"In the Kitchen","image":"dishes.jpg","audio":"dishes.mp3"},{"name":"Dishwasher","category":"In the Kitchen","image":"dishwasher.jpg","audio":"dishwasher.mp3"},{"name":"Electric oven","category":"In the Kitchen","image":"electric oven.jpg","audio":"electric oven.mp3"},{"name":"Fork","category":"In the Kitchen","image":"fork.jpg","audio":"fork.mp3"},{"name":"Fruit bowl","category":"In the Kitchen","image":"fruit bowl.jpg","audio":"fruit bowl.mp3"},{"name":"Frying pan","category":"In the Kitchen","image":"frying pan.jpg","audio":"frying pan.mp3"},{"name":"Funnel","category":"In the Kitchen","image":"funnel.jpg","audio":"funnel.mp3"},{"name":"Glass","category":"In the Kitchen","image":"glass.jpg","audio":"glass.mp3"},{"name":"Grater","category":"In the Kitchen","image":"grater.jpg","audio":"grater.mp3"},{"name":"Grill pan","category":"In the Kitchen","image":"grill pan.jpg","audio":"grill pan.mp3"},{"name":"Jars","category":"In the Kitchen","image":"jars.jpg","audio":"jars.mp3"},{"name":"Jug","category":"In the Kitchen","image":"jug.jpg","audio":"jug.mp3"},{"name":"Kettle","category":"In the Kitchen","image":"kettle.jpg","audio":"kettle.mp3"},{"name":"Knife","category":"In the Kitchen","image":"knife.jpg","audio":"knife.mp3"},{"name":"Ladle","category":"In the Kitchen","image":"ladle.jpg","audio":"ladle.mp3"},{"name":"Measuring cup","category":"In the Kitchen","image":"measuring cup.jpg","audio":"measuring cup.mp3"},{"name":"Microwave oven","category":"In the Kitchen","image":"microwave oven.jpg","audio":"microwave oven.mp3"},{"name":"Mitten (oven glove)","category":"In the Kitchen","image":"mitten (oven glove).jpg","audio":"mitten (oven glove).mp3"},{"name":"Mixer","category":"In the Kitchen","image":"mixer.jpg","audio":"mixer.mp3"},{"name":"Mug","category":"In the Kitchen","image":"mug.jpg","audio":"mug.mp3"},{"name":"Napkin","category":"In the Kitchen","image":"napkin.jpg","audio":"napkin.mp3"},{"name":"Pan","category":"In the Kitchen","image":"pan.jpg","audio":"pan.mp3"},{"name":"Peeler","category":"In the Kitchen","image":"peeler.jpg","audio":"peeler.mp3"},{"name":"Plate","category":"In the Kitchen","image":"plate.jpg","audio":"plate.mp3"},{"name":"Pot lid","category":"In the Kitchen","image":"pot lid.jpg","audio":"pot lid.mp3"},{"name":"Pot","category":"In the Kitchen","image":"pot.jpg","audio":"pot.mp3"},{"name":"Pressure cooker","category":"In the Kitchen","image":"pressure cooker.jpg","audio":"pressure cooker.mp3"},{"name":"Refrigerator","category":"In the Kitchen","image":"refrigerator.jpg","audio":"refrigerator.mp3"},{"name":"Rolling pin","category":"In the Kitchen","image":"rolling pin.jpg","audio":"rolling pin.mp3"},{"name":"Salt shaker","category":"In the Kitchen","image":"salt shaker.jpg","audio":"salt shaker.mp3"},{"name":"Sieve","category":"In the Kitchen","image":"sieve.jpg","audio":"sieve.mp3"},{"name":"Sink (kitchen sink)","category":"In the Kitchen","image":"sink (kitchen sink).jpg","audio":"sink (kitchen sink).mp3"},{"name":"Skimmer","category":"In the Kitchen","image":"skimmer.jpg","audio":"skimmer.mp3"},{"name":"Spatula","category":"In the Kitchen","image":"spatula.jpg","audio":"spatula.mp3"},{"name":"Sponge","category":"In the Kitchen","image":"sponge.jpg","audio":"sponge.mp3"},{"name":"Spoon","category":"In the Kitchen","image":"spoon.jpg","audio":"spoon.mp3"},{"name":"Squeezer","category":"In the Kitchen","image":"squeezer.jpg","audio":"squeezer.mp3"},{"name":"Stove","category":"In the Kitchen","image":"stove.jpg","audio":"stove.mp3"},{"name":"Table cloth","category":"In the Kitchen","image":"table cloth.jpg","audio":"table cloth.mp3"},{"name":"Tableware","category":"In the Kitchen","image":"tableware.jpg","audio":"tableware.mp3"},{"name":"Teapot","category":"In the Kitchen","image":"teapot.jpg","audio":"teapot.mp3"},{"name":"Toaster","category":"In the Kitchen","image":"toaster.jpg","audio":"toaster.mp3"},{"name":"Tray","category":"In the Kitchen","image":"tray.jpg","audio":"tray.mp3"}]},"Jobs & Occupations":{"name":"Jobs & Occupations","cover":{"name":"Jobs & Occupations","category":"Jobs & Occupations","image":"Jobs & Occupations.jpg","audio":"Jobs & Occupations.mp3"},"cards":[{"name":"Accountant","category":"Jobs & Occupations","image":"accountant.jpg","audio":"accountant.mp3"},{"name":"Actor","category":"Jobs & Occupations","image":"actor.jpg","audio":"actor.mp3"},{"name":"Actress","category":"Jobs & Occupations","image":"actress.jpg","audio":"actress.mp3"},{"name":"Architect","category":"Jobs & Occupations","image":"architect.jpg","audio":"architect.mp3"},{"name":"Artist","category":"Jobs & Occupations","image":"artist.jpg","audio":"artist.mp3"},{"name":"Baker","category":"Jobs & Occupations","image":"baker.jpg","audio":"baker.mp3"},{"name":"Ballerina","category":"Jobs & Occupations","image":"ballerina.jpg","audio":"ballerina.mp3"},{"name":"Businessman","category":"Jobs & Occupations","image":"businessman.jpg","audio":"businessman.mp3"},{"name":"Carpenter","category":"Jobs & Occupations","image":"carpenter.jpg","audio":"carpenter.mp3"},{"name":"Chef","category":"Jobs & Occupations","image":"chef.jpg","audio":"chef.mp3"},{"name":"Clown","category":"Jobs & Occupations","image":"clown.jpg","audio":"clown.mp3"},{"name":"Cook","category":"Jobs & Occupations","image":"cook.jpg","audio":"cook.mp3"},{"name":"Delivery boy","category":"Jobs & Occupations","image":"delivery boy.jpg","audio":"delivery boy.mp3"},{"name":"Doctor","category":"Jobs & Occupations","image":"doctor.jpg","audio":"doctor.mp3"},{"name":"Driver","category":"Jobs & Occupations","image":"driver.jpg","audio":"driver.mp3"},{"name":"Electrician","category":"Jobs & Occupations","image":"electrician.jpg","audio":"electrician.mp3"},{"name":"Engineer","category":"Jobs & Occupations","image":"engineer.jpg","audio":"engineer.mp3"},{"name":"Farmer","category":"Jobs & Occupations","image":"farmer.jpg","audio":"farmer.mp3"},{"name":"Firefighter","category":"Jobs & Occupations","image":"firefighter.jpg","audio":"firefighter.mp3"},{"name":"Flight attendant","category":"Jobs & Occupations","image":"flight attendant.jpg","audio":"flight attendant.mp3"},{"name":"Hairdresser","category":"Jobs & Occupations","image":"hairdresser.jpg","audio":"hairdresser.mp3"},{"name":"Lawyer","category":"Jobs & Occupations","image":"lawyer.jpg","audio":"lawyer.mp3"},{"name":"Lifeguard","category":"Jobs & Occupations","image":"lifeguard.jpg","audio":"lifeguard.mp3"},{"name":"Magician","category":"Jobs & Occupations","image":"magician.jpg","audio":"magician.mp3"},{"name":"Maid","category":"Jobs & Occupations","image":"maid.jpg","audio":"maid.mp3"},{"name":"Musician","category":"Jobs & Occupations","image":"musician.jpg","audio":"musician.mp3"},{"name":"Nurse","category":"Jobs & Occupations","image":"nurse.jpg","audio":"nurse.mp3"},{"name":"Photographer","category":"Jobs & Occupations","image":"photographer.jpg","audio":"photographer.mp3"},{"name":"Physiotherapist","category":"Jobs & Occupations","image":"Physiotherapist.jpg","audio":false},{"name":"Pilot","category":"Jobs & Occupations","image":"pilot.jpg","audio":"pilot.mp3"},{"name":"Plumber","category":"Jobs & Occupations","image":"plumber.jpg","audio":"plumber.mp3"},{"name":"Policeman","category":"Jobs & Occupations","image":"policeman.jpg","audio":"policeman.mp3"},{"name":"Politician","category":"Jobs & Occupations","image":"politician.jpg","audio":"politician.mp3"},{"name":"Psychologist","category":"Jobs & Occupations","image":"psychologist.jpg","audio":"psychologist.mp3"},{"name":"Race driver","category":"Jobs & Occupations","image":"race driver.jpg","audio":"race driver.mp3"},{"name":"Receptionist","category":"Jobs & Occupations","image":"receptionist.jpg","audio":"receptionist.mp3"},{"name":"Reporter","category":"Jobs & Occupations","image":"reporter.jpg","audio":"reporter.mp3"},{"name":"Scientist","category":"Jobs & Occupations","image":"scientist.jpg","audio":"scientist.mp3"},{"name":"Secretary","category":"Jobs & Occupations","image":"secretary.jpg","audio":"secretary.mp3"},{"name":"Shop assistant","category":"Jobs & Occupations","image":"shop assistant.jpg","audio":"shop assistant.mp3"},{"name":"Singer","category":"Jobs & Occupations","image":"singer.jpg","audio":"singer.mp3"},{"name":"Soccer player","category":"Jobs & Occupations","image":"soccer player.jpg","audio":"soccer player.mp3"},{"name":"Teacher","category":"Jobs & Occupations","image":"teacher.jpg","audio":"teacher.mp3"},{"name":"Therapist","category":"Jobs & Occupations","image":"Therapist.jpg","audio":false},{"name":"Tour guide","category":"Jobs & Occupations","image":"tour guide.jpg","audio":"tour guide.mp3"},{"name":"Vet","category":"Jobs & Occupations","image":"vet.jpg","audio":"vet.mp3"},{"name":"Waiter","category":"Jobs & Occupations","image":"waiter.jpg","audio":"waiter.mp3"},{"name":"Web designer","category":"Jobs & Occupations","image":"web designer.jpg","audio":"web designer.mp3"},{"name":"Worker","category":"Jobs & Occupations","image":"worker.jpg","audio":"worker.mp3"}]},"Pets":{"name":"Pets","cover":{"name":"Pets","category":"Pets","image":"Pets.jpg","audio":"Pets.mp3"},"cards":[{"name":"Baby cow","category":"Pets","image":"baby cow.jpg","audio":"baby cow.mp3"},{"name":"Bunny","category":"Pets","image":"bunny.jpg","audio":"bunny.mp3"},{"name":"Chick","category":"Pets","image":"chick.jpg","audio":"chick.mp3"},{"name":"Cockatoo","category":"Pets","image":"Cockatoo.jpg","audio":"Cockatoo.mp3"},{"name":"Goat kid","category":"Pets","image":"goat kid.jpg","audio":"goat kid.mp3"},{"name":"Golden fish","category":"Pets","image":"golden fish.jpg","audio":"golden fish.mp3"},{"name":"Guinea pig","category":"Pets","image":"guinea pig.jpg","audio":"guinea pig.mp3"},{"name":"Hamster","category":"Pets","image":"hamster.jpg","audio":"hamster.mp3"},{"name":"Kittens","category":"Pets","image":"kittens.jpg","audio":"kittens.mp3"},{"name":"Lamb","category":"Pets","image":"lamb.jpg","audio":"lamb.mp3"},{"name":"Lion cub","category":"Pets","image":"lion cub.jpg","audio":"lion cub.mp3"},{"name":"Macaw","category":"Pets","image":"macaw.jpg","audio":"macaw.mp3"},{"name":"Panda","category":"Pets","image":"panda.jpg","audio":"panda.mp3"},{"name":"Parrot","category":"Pets","image":"Parrot.jpg","audio":"Parrot.mp3"},{"name":"Piglet","category":"Pets","image":"piglet.jpg","audio":"piglet.mp3"},{"name":"Puppy","category":"Pets","image":"puppy.jpg","audio":"puppy.mp3"},{"name":"Tiger cub","category":"Pets","image":"tiger cub.jpg","audio":"tiger cub.mp3"},{"name":"Turtle","category":"Pets","image":"Turtle.jpg","audio":"Turtle.mp3"}]},"School Material-School Items":{"name":"School Material-School Items","cover":{"name":"School Material-School Items","category":"School Material-School Items","image":"School Material-School Items.jpg","audio":"School Material-School Items.mp3"},"cards":[{"name":"Backpack","category":"School Material-School Items","image":"backpack.jpg","audio":"backpack.mp3"},{"name":"Ball point pen","category":"School Material-School Items","image":"ball point pen.jpg","audio":"ball point pen.mp3"},{"name":"Binder","category":"School Material-School Items","image":"binder.jpg","audio":"binder.mp3"},{"name":"Black pencil","category":"School Material-School Items","image":"black pencil.jpg","audio":"black pencil.mp3"},{"name":"Book","category":"School Material-School Items","image":"book.jpg","audio":"book.mp3"},{"name":"Calculator","category":"School Material-School Items","image":"calculator.jpg","audio":"calculator.mp3"},{"name":"Chalk board","category":"School Material-School Items","image":"chalk board.jpg","audio":"chalk board.mp3"},{"name":"Chalk","category":"School Material-School Items","image":"chalk.jpg","audio":"chalk.mp3"},{"name":"Colored pencils","category":"School Material-School Items","image":"colored pencils.jpg","audio":"colored pencils.mp3"},{"name":"Crayons","category":"School Material-School Items","image":"crayons.jpg","audio":"crayons.mp3"},{"name":"Dictionary","category":"School Material-School Items","image":"dictionary.jpg","audio":"dictionary.mp3"},{"name":"Eraser","category":"School Material-School Items","image":"eraser.jpg","audio":"eraser.mp3"},{"name":"Folder","category":"School Material-School Items","image":"folder.jpg","audio":"folder.mp3"},{"name":"Glue","category":"School Material-School Items","image":"glue.jpg","audio":"glue.mp3"},{"name":"Highlighter","category":"School Material-School Items","image":"highlighter.jpg","audio":"highlighter.mp3"},{"name":"Map of the world","category":"School Material-School Items","image":"map of the world.jpg","audio":"map of the world.mp3"},{"name":"Marker","category":"School Material-School Items","image":"marker.jpg","audio":"marker.mp3"},{"name":"Mechanical pencil","category":"School Material-School Items","image":"mechanical pencil.jpg","audio":"mechanical pencil.mp3"},{"name":"Notebook - copybook","category":"School Material-School Items","image":"notebook - copybook.jpg","audio":"notebook - copybook.mp3"},{"name":"Paper clips","category":"School Material-School Items","image":"paper clips.jpg","audio":"paper clips.mp3"},{"name":"Paper","category":"School Material-School Items","image":"paper.jpg","audio":"paper.mp3"},{"name":"Pen","category":"School Material-School Items","image":"pen.jpg","audio":"pen.mp3"},{"name":"Pencil case","category":"School Material-School Items","image":"pencil case.jpg","audio":"pencil case.mp3"},{"name":"Ruler","category":"School Material-School Items","image":"ruler.jpg","audio":"ruler.mp3"},{"name":"Scissors","category":"School Material-School Items","image":"scissors.jpg","audio":"scissors.mp3"},{"name":"Sharpener","category":"School Material-School Items","image":"sharpener.jpg","audio":"sharpener.mp3"},{"name":"Stapler","category":"School Material-School Items","image":"stapler.jpg","audio":"stapler.mp3"},{"name":"Staples","category":"School Material-School Items","image":"staples.jpg","audio":"staples.mp3"},{"name":"Sticking tape","category":"School Material-School Items","image":"sticking tape.jpg","audio":"sticking tape.mp3"}]},"Technology":{"name":"Technology","cover":false,"cards":[{"name":"Cellphone","category":"Technology","image":"cellphone.jpg","audio":"cellphone.mp3"},{"name":"Computers","category":"Technology","image":"computers.jpg","audio":"computers.mp3"},{"name":"Desktop","category":"Technology","image":"desktop.jpg","audio":"desktop.mp3"},{"name":"Digital camera","category":"Technology","image":"digital camera.jpg","audio":"digital camera.mp3"},{"name":"Drone","category":"Technology","image":"drone.jpg","audio":"drone.mp3"},{"name":"Earphones","category":"Technology","image":"earphones.jpg","audio":"earphones.mp3"},{"name":"GPS","category":"Technology","image":"GPS.jpg","audio":"GPS.mp3"},{"name":"Headphones","category":"Technology","image":"headphones.jpg","audio":"headphones.mp3"},{"name":"Laptop","category":"Technology","image":"laptop.jpg","audio":"laptop.mp3"},{"name":"Memory card","category":"Technology","image":"memory card.jpg","audio":"memory card.mp3"},{"name":"Memory stick","category":"Technology","image":"memory stick.jpg","audio":"memory stick.mp3"},{"name":"Microphone","category":"Technology","image":"microphone.jpg","audio":"microphone.mp3"},{"name":"Microscope","category":"Technology","image":"microscope.jpg","audio":"microscope.mp3"},{"name":"Printer","category":"Technology","image":"printer.jpg","audio":"printer.mp3"},{"name":"Radar","category":"Technology","image":"radar.jpg","audio":"radar.mp3"},{"name":"Robot","category":"Technology","image":"robot.jpg","audio":"robot.mp3"},{"name":"Satellite","category":"Technology","image":"satellite.jpg","audio":"satellite.mp3"},{"name":"Spaceship","category":"Technology","image":"spaceship.jpg","audio":"spaceship.mp3"},{"name":"Techonogy","category":"Technology","image":"Techonogy.jpg","audio":"Techonogy.mp3"},{"name":"Telescope","category":"Technology","image":"telescope.jpg","audio":"telescope.mp3"},{"name":"Tomography","category":"Technology","image":"tomography.jpg","audio":"tomography.mp3"},{"name":"Webcam","category":"Technology","image":"webcam.jpg","audio":"webcam.mp3"}]},"Tools":{"name":"Tools","cover":{"name":"Tools","category":"Tools","image":"Tools.jpg","audio":"Tools.mp3"},"cards":[{"name":"Bottle opener","category":"Tools","image":"bottle opener.jpg","audio":"bottle opener.mp3"},{"name":"Briefcase","category":"Tools","image":"briefcase.jpg","audio":"briefcase.mp3"},{"name":"Broom","category":"Tools","image":"broom.jpg","audio":"broom.mp3"},{"name":"Chain saw","category":"Tools","image":"chain saw.jpg","audio":"chain saw.mp3"},{"name":"Compass","category":"Tools","image":"compass.jpg","audio":"compass.mp3"},{"name":"Computer","category":"Tools","image":"computer.jpg","audio":"computer.mp3"},{"name":"Corkscrew","category":"Tools","image":"corkscrew.jpg","audio":"corkscrew.mp3"},{"name":"Crowbar","category":"Tools","image":"crowbar.jpg","audio":"crowbar.mp3"},{"name":"Drill","category":"Tools","image":"drill.jpg","audio":"drill.mp3"},{"name":"Drums","category":"Tools","image":"drums.jpg","audio":"drums.mp3"},{"name":"Eyedropper","category":"Tools","image":"eyedropper.jpg","audio":"eyedropper.mp3"},{"name":"Fishhook","category":"Tools","image":"fishhook.jpg","audio":"fishhook.mp3"},{"name":"Fishing net","category":"Tools","image":"fishing net.jpg","audio":"fishing net.mp3"},{"name":"Fishing rod","category":"Tools","image":"fishing rod.jpg","audio":"fishing rod.mp3"},{"name":"Gardener fork","category":"Tools","image":"gardener fork.jpg","audio":"gardener fork.mp3"},{"name":"Glasses","category":"Tools","image":"glasses.jpg","audio":"glasses.mp3"},{"name":"Guitar","category":"Tools","image":"guitar.jpg","audio":"guitar.mp3"},{"name":"Gun (handgun)","category":"Tools","image":"gun (handgun).jpg","audio":"gun (handgun).mp3"},{"name":"Hair-cutting scissors","category":"Tools","image":"hair-cutting scissors.jpg","audio":"hair-cutting scissors.mp3"},{"name":"Hammer","category":"Tools","image":"hammer.jpg","audio":"hammer.mp3"},{"name":"Handsaw","category":"Tools","image":"handsaw.jpg","audio":"handsaw.mp3"},{"name":"Hard hat","category":"Tools","image":"hard hat.jpg","audio":"hard hat.mp3"},{"name":"Hoe","category":"Tools","image":"hoe.jpg","audio":"hoe.mp3"},{"name":"Iron","category":"Tools","image":"iron.jpg","audio":"iron.mp3"},{"name":"Ladder","category":"Tools","image":"ladder.jpg","audio":"ladder.mp3"},{"name":"Microphone","category":"Tools","image":"microphone.jpg","audio":"microphone.mp3"},{"name":"Notice board","category":"Tools","image":"notice board.jpg","audio":"notice board.mp3"},{"name":"Paintbrush","category":"Tools","image":"paintbrush.jpg","audio":"paintbrush.mp3"},{"name":"Paper punch","category":"Tools","image":"paper punch.jpg","audio":"paper punch.mp3"},{"name":"Pliers","category":"Tools","image":"pliers.jpg","audio":"pliers.mp3"},{"name":"Printer","category":"Tools","image":"printer.jpg","audio":"printer.mp3"},{"name":"Projector","category":"Tools","image":"projector.jpg","audio":"projector.mp3"},{"name":"Rake","category":"Tools","image":"rake.jpg","audio":"rake.mp3"},{"name":"Rubber stamp","category":"Tools","image":"rubber stamp.jpg","audio":"rubber stamp.mp3"},{"name":"Scale","category":"Tools","image":"scale.jpg","audio":"scale.mp3"},{"name":"Screw driver","category":"Tools","image":"screw driver.jpg","audio":"screw driver.mp3"},{"name":"Sewing machine","category":"Tools","image":"sewing machine.jpg","audio":"sewing machine.mp3"},{"name":"Shovel","category":"Tools","image":"shovel.jpg","audio":"shovel.mp3"},{"name":"Stethoscope","category":"Tools","image":"stethoscope.jpg","audio":"stethoscope.mp3"},{"name":"Sticky notes","category":"Tools","image":"sticky notes.jpg","audio":"sticky notes.mp3"},{"name":"Syringe","category":"Tools","image":"syringe.jpg","audio":"syringe.mp3"},{"name":"Tape dispenser","category":"Tools","image":"tape dispenser.jpg","audio":"tape dispenser.mp3"},{"name":"Tape measure","category":"Tools","image":"tape measure.jpg","audio":"tape measure.mp3"},{"name":"Thermometer","category":"Tools","image":"thermometer.jpg","audio":"thermometer.mp3"},{"name":"Tractor","category":"Tools","image":"tractor.jpg","audio":"tractor.mp3"},{"name":"Tweezers","category":"Tools","image":"tweezers.jpg","audio":"tweezers.mp3"},{"name":"Wastebasket","category":"Tools","image":"wastebasket.jpg","audio":"wastebasket.mp3"},{"name":"Water hose","category":"Tools","image":"water hose.jpg","audio":"water hose.mp3"},{"name":"Wheelbarrow","category":"Tools","image":"wheelbarrow.jpg","audio":"wheelbarrow.mp3"},{"name":"Wrench","category":"Tools","image":"wrench.jpg","audio":"wrench.mp3"},{"name":"Wrenches","category":"Tools","image":"wrenches.jpg","audio":"wrenches.mp3"},{"name":"Xerox (copier)","category":"Tools","image":"xerox (copier).jpg","audio":"xerox (copier).mp3"}]},"Toys":{"name":"Toys","cover":{"name":"Toys","category":"Toys","image":"Toys.jpg","audio":"Toys.mp3"},"cards":[{"name":"Alphabet blocks","category":"Toys","image":"alphabet blocks.jpg","audio":"alphabet blocks.mp3"},{"name":"Ball","category":"Toys","image":"ball.jpg","audio":"ball.mp3"},{"name":"Balloon","category":"Toys","image":"balloon.jpg","audio":"balloon.mp3"},{"name":"Bridge","category":"Toys","image":"bridge.jpg","audio":"bridge.mp3"},{"name":"Bucket and shovel","category":"Toys","image":"bucket and shovel.jpg","audio":"bucket and shovel.mp3"},{"name":"Building blocks","category":"Toys","image":"building blocks.jpg","audio":"building blocks.mp3"},{"name":"Carrousel","category":"Toys","image":"carrousel.jpg","audio":"carrousel.mp3"},{"name":"Climber","category":"Toys","image":"climber.jpg","audio":"climber.mp3"},{"name":"Doll","category":"Toys","image":"doll.jpg","audio":"doll.mp3"},{"name":"Hide and seek","category":"Toys","image":"hide and seek.jpg","audio":"hide and seek.mp3"},{"name":"Hopscotch","category":"Toys","image":"hopscotch.jpg","audio":"hopscotch.mp3"},{"name":"Kite","category":"Toys","image":"kite.jpg","audio":"kite.mp3"},{"name":"Ladder","category":"Toys","image":"ladder.jpg","audio":"ladder.mp3"},{"name":"Marbles","category":"Toys","image":"marbles.jpg","audio":"marbles.mp3"},{"name":"Monkey bars","category":"Toys","image":"monkey bars.jpg","audio":"monkey bars.mp3"},{"name":"Rocking horse","category":"Toys","image":"rocking horse.jpg","audio":"rocking horse.mp3"},{"name":"Sand box","category":"Toys","image":"Sand box.jpg","audio":"Sand box.mp3"},{"name":"See-saw","category":"Toys","image":"see-saw.jpg","audio":"see-saw.mp3"},{"name":"Skip rope","category":"Toys","image":"skip rope.jpg","audio":"skip rope.mp3"},{"name":"Skipping rope","category":"Toys","image":"skipping rope.jpg","audio":"skipping rope.mp3"},{"name":"Slide","category":"Toys","image":"slide.jpg","audio":"slide.mp3"},{"name":"Spinning top","category":"Toys","image":"spinning top.jpg","audio":"spinning top.mp3"},{"name":"Swing set","category":"Toys","image":"swing set.jpg","audio":"swing set.mp3"},{"name":"Swing","category":"Toys","image":"swing.jpg","audio":"swing.mp3"},{"name":"Teddy bear","category":"Toys","image":"Teddy bear.jpg","audio":"Teddy bear.mp3"},{"name":"Toy bike","category":"Toys","image":"toy bike.jpg","audio":"toy bike.mp3"},{"name":"Toy car","category":"Toys","image":"toy car.jpg","audio":"toy car.mp3"},{"name":"Toy dinosaur","category":"Toys","image":"toy dinosaur.jpg","audio":"toy dinosaur.mp3"},{"name":"Toy drum","category":"Toys","image":"toy drum.jpg","audio":"toy drum.mp3"},{"name":"Toy duck","category":"Toys","image":"toy duck.jpg","audio":"toy duck.mp3"},{"name":"Toy helicopter","category":"Toys","image":"toy helicopter.jpg","audio":"toy helicopter.mp3"},{"name":"Toy plane","category":"Toys","image":"toy plane.jpg","audio":"toy plane.mp3"},{"name":"Toy robot","category":"Toys","image":"toy robot.jpg","audio":"toy robot.mp3"},{"name":"Toy rocket","category":"Toys","image":"toy rocket.jpg","audio":"toy rocket.mp3"},{"name":"Toy soldier","category":"Toys","image":"toy soldier.jpg","audio":"toy soldier.mp3"},{"name":"Toy train","category":"Toys","image":"toy train.jpg","audio":"toy train.mp3"},{"name":"Toy truck","category":"Toys","image":"toy truck.jpg","audio":"toy truck.mp3"},{"name":"Trampoline","category":"Toys","image":"trampoline.jpg","audio":"trampoline.mp3"},{"name":"Tube slide","category":"Toys","image":"tube slide.jpg","audio":"tube slide.mp3"},{"name":"Tug of war","category":"Toys","image":"tug of war.jpg","audio":"tug of war.mp3"},{"name":"Tunnel","category":"Toys","image":"tunnel.jpg","audio":"tunnel.mp3"},{"name":"Yo yo","category":"Toys","image":"yo yo.jpg","audio":false}]},"Wild Animals":{"name":"Wild Animals","cover":{"name":"Wild Animals","category":"Wild Animals","image":"Wild Animals.jpg","audio":"Wild Animals.mp3"},"cards":[{"name":"Anaconda","category":"Wild Animals","image":"anaconda.jpg","audio":"anaconda.mp3"},{"name":"Anteater","category":"Wild Animals","image":"anteater.jpg","audio":"anteater.mp3"},{"name":"Armadillo","category":"Wild Animals","image":"armadillo.jpg","audio":"armadillo.mp3"},{"name":"Bear","category":"Wild Animals","image":"bear.jpg","audio":"bear.mp3"},{"name":"Beaver","category":"Wild Animals","image":"beaver.jpg","audio":"beaver.mp3"},{"name":"Buffalo","category":"Wild Animals","image":"buffalo.jpg","audio":"buffalo.mp3"},{"name":"Camel","category":"Wild Animals","image":"camel.jpg","audio":"camel.mp3"},{"name":"Capybara","category":"Wild Animals","image":"capybara.jpg","audio":"capybara.mp3"},{"name":"Chimpanzee","category":"Wild Animals","image":"chimpanzee.jpg","audio":"chimpanzee.mp3"},{"name":"Crab","category":"Wild Animals","image":"crab.jpg","audio":"crab.mp3"},{"name":"Crocodile","category":"Wild Animals","image":"crocodile.jpg","audio":"crocodile.mp3"},{"name":"Deer","category":"Wild Animals","image":"deer.jpg","audio":"deer.mp3"},{"name":"Dinosaur","category":"Wild Animals","image":"dinosaur.jpg","audio":"dinosaur.mp3"},{"name":"Dolphin","category":"Wild Animals","image":"dolphin.jpg","audio":"dolphin.mp3"},{"name":"Dove","category":"Wild Animals","image":"dove.jpg","audio":"dove.mp3"},{"name":"Eagle","category":"Wild Animals","image":"eagle.jpg","audio":"eagle.mp3"},{"name":"Elephant","category":"Wild Animals","image":"elephant.jpg","audio":"elephant.mp3"},{"name":"Fox","category":"Wild Animals","image":"fox.jpg","audio":"fox.mp3"},{"name":"Giraffe","category":"Wild Animals","image":"giraffe.jpg","audio":"giraffe.mp3"},{"name":"Gorilla","category":"Wild Animals","image":"gorilla.jpg","audio":false},{"name":"Hawk","category":"Wild Animals","image":"hawk.jpg","audio":"hawk.mp3"},{"name":"Hippo","category":"Wild Animals","image":"hippo.jpg","audio":"hippo.mp3"},{"name":"Hyena","category":"Wild Animals","image":"hyena.jpg","audio":"hyena.mp3"},{"name":"Kangaroo","category":"Wild Animals","image":"kangaroo.jpg","audio":"kangaroo.mp3"},{"name":"Leopard","category":"Wild Animals","image":"leopard.jpg","audio":"leopard.mp3"},{"name":"Lion","category":"Wild Animals","image":"lion.jpg","audio":"lion.mp3"},{"name":"Lizard","category":"Wild Animals","image":"lizard.jpg","audio":"lizard.mp3"},{"name":"Monkey","category":"Wild Animals","image":"monkey.jpg","audio":"monkey.mp3"},{"name":"Ostrich","category":"Wild Animals","image":"ostrich.jpg","audio":"ostrich.mp3"},{"name":"Owl","category":"Wild Animals","image":"owl.jpg","audio":"owl.mp3"},{"name":"Penguin","category":"Wild Animals","image":"penguin.jpg","audio":"penguin.mp3"},{"name":"Porcupine","category":"Wild Animals","image":"porcupine.jpg","audio":"porcupine.mp3"},{"name":"Possum","category":"Wild Animals","image":"possum.jpg","audio":"possum.mp3"},{"name":"Rhino","category":"Wild Animals","image":"rhino.jpg","audio":"rhino.mp3"},{"name":"Seal","category":"Wild Animals","image":"seal.jpg","audio":"seal.mp3"},{"name":"Shark","category":"Wild Animals","image":"shark.jpg","audio":"shark.mp3"},{"name":"Snakes","category":"Wild Animals","image":"snakes.jpg","audio":"snakes.mp3"},{"name":"Squirrel","category":"Wild Animals","image":"squirrel.jpg","audio":"squirrel.mp3"},{"name":"Starfish","category":"Wild Animals","image":"starfish.jpg","audio":"starfish.mp3"},{"name":"Tiger","category":"Wild Animals","image":"tiger.jpg","audio":"tiger.mp3"},{"name":"Turtle","category":"Wild Animals","image":"turtle.jpg","audio":"turtle.mp3"},{"name":"Warthog","category":"Wild Animals","image":"warthog.jpg","audio":"warthog.mp3"},{"name":"Whale","category":"Wild Animals","image":"whale.jpg","audio":"whale.mp3"},{"name":"Wolf","category":"Wild Animals","image":"wolf.jpg","audio":"wolf.mp3"},{"name":"Zebra","category":"Wild Animals","image":"zebra.jpg","audio":"zebra.mp3"}]}},"cards":[]}